simo_komfovent/__init__.py
simo_komfovent/apps.py
simo_komfovent/controllers.py
simo_komfovent/forms.py
simo_komfovent/gateways.py
simo_komfovent/models.py
simo_komfovent/tasks.py
simo_komfovent/utils.py
simo_komfovent/__pycache__/__init__.cpython-312.pyc
simo_komfovent/__pycache__/__init__.cpython-38.pyc
simo_komfovent/__pycache__/apps.cpython-312.pyc
simo_komfovent/__pycache__/apps.cpython-38.pyc
simo_komfovent/__pycache__/controllers.cpython-312.pyc
simo_komfovent/__pycache__/controllers.cpython-38.pyc
simo_komfovent/__pycache__/forms.cpython-312.pyc
simo_komfovent/__pycache__/forms.cpython-38.pyc
simo_komfovent/__pycache__/gateways.cpython-312.pyc
simo_komfovent/__pycache__/gateways.cpython-38.pyc
simo_komfovent/__pycache__/models.cpython-312.pyc
simo_komfovent/__pycache__/models.cpython-38.pyc
simo_komfovent/__pycache__/utils.cpython-312.pyc
simo_komfovent/__pycache__/utils.cpython-38.pyc
simo_komfovent-1.1.7.dist-info/LICENSE.md
simo_komfovent-1.1.7.dist-info/METADATA
simo_komfovent-1.1.7.dist-info/WHEEL
simo_komfovent-1.1.7.dist-info/top_level.txt
simo_komfovent-1.1.7.dist-info/RECORD
