Metadata-Version: 2.1
Name: simo-komfovent
Version: 1.1.7
Summary: Komfovent C6 integration for SIMO.io
Author-email: Simanas Venčkauskas <simanas@simo.io>
Project-URL: Homepage, https://github.com/SIMO-io/simo-komfovent
Project-URL: Issues, https://github.com/SIMO-io/simo-komfovent/issues
Classifier: Programming Language :: Python :: 3
Classifier: License :: OSI Approved :: MIT License
Classifier: Operating System :: OS Independent
Requires-Python: >=3.8
License-File: LICENSE.md
Requires-Dist: simo>=2.5.32
Requires-Dist: beautifulsoup4>=4.12.2
Requires-Dist: lxml>=4.9.4
